Metadata-Version: 1.0
Name: distributions-gauss-lt
Version: 0.1
Summary: Gaussian distributions
Home-page: UNKNOWN
Author: Li Tang
Author-email: tangli666@gmail.com
License: UNKNOWN
Platform: UNKNOWN
